binary_stream/__init__.py
binary_stream/binary_stream.py
binary_stream-1.0.1.dist-info/LICENSE
binary_stream-1.0.1.dist-info/METADATA
binary_stream-1.0.1.dist-info/WHEEL
binary_stream-1.0.1.dist-info/top_level.txt
binary_stream-1.0.1.dist-info/RECORD
